COPYING
README.md
pyproject.toml
setup.cfg
setup.py
src/rockmate/__init__.py
src/rockmate/compiler.py
src/rockmate/frontend.py
src/rockmate/op_schedule.py
src/rockmate/rockmate.py
src/rockmate/simulation.py
src/rockmate/test.py
src/rockmate/utils.py
src/rockmate.egg-info/PKG-INFO
src/rockmate.egg-info/SOURCES.txt
src/rockmate.egg-info/dependency_links.txt
src/rockmate.egg-info/requires.txt
src/rockmate.egg-info/top_level.txt
src/rockmate/solvers/__init__.py
src/rockmate/solvers/cheap.py
src/rockmate/solvers/main.py
src/rockmate/solvers/setup.py
src/rockmate/solvers/twremat.py
src/rockmate/solvers/twremat_utils.py
src/rockmate/solvers/ilp/__init__.py
src/rockmate/solvers/ilp/ilp_model.py
src/rockmate/solvers/ilp/ilp_offload.py
src/rockmate/solvers/ilp/ilp_schedule.py
src/rockmate/solvers/ilp/ilp_solver.py
src/rockmate/solvers/ilp/ilp_utils.py
src/rockmate/solvers/rk_rotor/__init__.py
src/rockmate/solvers/rk_rotor/csequence.py
src/rockmate/solvers/rk_rotor/def_chain.py
src/rockmate/solvers/rk_rotor/def_sequence.py
src/rockmate/solvers/rk_rotor/rk_rotor.py
src/rockmate/solvers/rk_rotor/rotor_solver.py
src/rockmate/solvers/rk_rotor/solver.c