Metadata-Version: 2.1
Name: rockmate
Version: 2.0.0
Summary: Efficient and Automatic Rematerialization for Pytorch training
Author: Théotime Le Hellard, Xunyi Zhao, Julia Gusak, Li Zhe, Olivier Beaumont, Lionel Eyraud-Dubois
Maintainer-email: Lionel Eyraud-Dubois <lionel.eyraud-dubois@inria.fr>
License: MIT License
Project-URL: Repository, https://github.com/topal-team/rockmate.git
Keywords: rematerialization,training,pytorch,memory
Requires-Python: >=3.8
License-File: COPYING
Requires-Dist: numpy
Requires-Dist: torch>=1.7
Requires-Dist: rkgb>=2.0.0
Requires-Dist: pulp==2.7.0
Requires-Dist: configmypy>=0.2.0
